<Properties StartupConfiguration="{E22E0FF3-89A5-4E27-8B4C-3B06E9C581AE}|Unit Tests">
  <MonoDevelop.Ide.ItemProperties.sample PreferredExecutionTarget="MonoDevelop.Default" />
  <MonoDevelop.Ide.Workbench ActiveDocument="sample/Pages/DeletingCurrentCardPage.cs">
    <Files>
      <File FileName="sample/AddCardToTestListTest.cs" Line="29" Column="53" />
      <File FileName="sample/EditNameOfCardTest.cs" Line="20" Column="12" />
      <File FileName="sample/Pages/EditNameOfCardTestPage.cs" Line="2" Column="1" />
      <File FileName="sample/DeleteCurrentCard.cs" Line="25" Column="31" />
      <File FileName="sample/Pages/DeletingCurrentCardPage.cs" Line="2" Column="93" />
    </Files>
    <Pads>
      <Pad Id="ProjectPad">
        <State name="__root__">
          <Node name="sample" expanded="True">
            <Node name="sample" expanded="True">
              <Node name="Pages" expanded="True">
                <Node name="DeletingCurrentCardPage.cs" selected="True" />
              </Node>
            </Node>
          </Node>
        </State>
      </Pad>
      <Pad Id="MonoDevelop.UnitTesting.TestPad">
        <State name="__root__">
          <Node name="sample" expanded="True">
            <Node name="sample" expanded="True">
              <Node name="sample" expanded="True">
                <Node name="addCardToTestBoardPageTest(Android)" expanded="True" />
                <Node name="AddCardToTestListTest(Android)" expanded="True" />
                <Node name="AddListTest(Android)" expanded="True" />
                <Node name="EditNameOfCardTest(Android)" expanded="True">
                  <Node name="EditNameOfCard" selected="True" />
                </Node>
                <Node name="Tests(Android)" expanded="True" />
              </Node>
            </Node>
          </Node>
        </State>
      </Pad>
    </Pads>
  </MonoDevelop.Ide.Workbench>
  <MonoDevelop.Ide.DebuggingService.PinnedWatches />
  <MonoDevelop.Ide.Workspace ActiveConfiguration="Debug" />
  <Debugger.DebugSourceFolders />
  <MonoDevelop.Ide.DebuggingService.Breakpoints>
    <BreakpointStore />
  </MonoDevelop.Ide.DebuggingService.Breakpoints>
  <MultiItemStartupConfigurations />
</Properties>